picollm/LICENSE
picollm/__init__.py
picollm/_factory.py
picollm/_picollm.py
picollm/_util.py
picollm/lib/linux/x86_64/libpv_picollm.so
picollm/lib/mac/arm64/libpv_picollm.dylib
picollm/lib/mac/x86_64/libpv_picollm.dylib
picollm/lib/raspberry-pi/cortex-a53/libpv_picollm.so
picollm/lib/raspberry-pi/cortex-a53-aarch64/libpv_picollm.so
picollm/lib/raspberry-pi/cortex-a72/libpv_picollm.so
picollm/lib/raspberry-pi/cortex-a72-aarch64/libpv_picollm.so
picollm/lib/raspberry-pi/cortex-a76/libpv_picollm.so
picollm/lib/raspberry-pi/cortex-a76-aarch64/libpv_picollm.so
picollm/lib/windows/amd64/libpv_picollm.dll
picollm/lib/windows/amd64/pv_ypu_impl_cuda.dll
picollm/lib/windows/arm64/libpv_picollm.dll
picollm-2.0.0.dist-info/METADATA
picollm-2.0.0.dist-info/WHEEL
picollm-2.0.0.dist-info/top_level.txt
picollm-2.0.0.dist-info/RECORD
