Metadata-Version: 2.4
Name: picollm
Version: 2.0.0
Summary: picoLLM Inference Engine
Home-page: https://github.com/Picovoice/picollm
Author: Picovoice
Author-email: hello@picovoice.ai
Keywords: Large Language Model,LLM,Generative AI,GenAI,Llama,Mistral,Mixtral,Gemma,Phi
Classifier: Development Status :: 5 - Production/Stable
Classifier: Intended Audience :: Developers
Classifier: License :: OSI Approved :: Apache Software License
Classifier: Operating System :: OS Independent
Classifier: Programming Language :: Python :: 3
Classifier: Topic :: Scientific/Engineering :: Artificial Intelligence
Requires-Python: >=3.9
Dynamic: author
Dynamic: author-email
Dynamic: classifier
Dynamic: description
Dynamic: description-content-type
Dynamic: home-page
Dynamic: keywords
Dynamic: requires-python
Dynamic: summary
